qiniu/__init__.py
qiniu/auth.py
qiniu/compat.py
qiniu/config.py
qiniu/main.py
qiniu/region.py
qiniu/utils.py
qiniu/zone.py
qiniu/http/__init__.py
qiniu/http/client.py
qiniu/http/default_client.py
qiniu/http/endpoint.py
qiniu/http/endpoints_provider.py
qiniu/http/endpoints_retry_policy.py
qiniu/http/region.py
qiniu/http/regions_provider.py
qiniu/http/regions_retry_policy.py
qiniu/http/response.py
qiniu/http/single_flight.py
qiniu/http/middleware/__init__.py
qiniu/http/middleware/base.py
qiniu/http/middleware/retry_domains.py
qiniu/http/middleware/ua.py
qiniu/retry/__init__.py
qiniu/retry/attempt.py
qiniu/retry/retrier.py
qiniu/retry/abc/__init__.py
qiniu/retry/abc/policy.py
qiniu/services/__init__.py
qiniu/services/cdn/__init__.py
qiniu/services/cdn/manager.py
qiniu/services/compute/__init__.py
qiniu/services/compute/app.py
qiniu/services/compute/config.py
qiniu/services/compute/qcos_api.py
qiniu/services/pili/__init__.py
qiniu/services/pili/rtc_server_manager.py
qiniu/services/processing/__init__.py
qiniu/services/processing/cmd.py
qiniu/services/processing/pfop.py
qiniu/services/sms/__init__.py
qiniu/services/sms/sms.py
qiniu/services/storage/__init__.py
qiniu/services/storage/_bucket_default_retrier.py
qiniu/services/storage/bucket.py
qiniu/services/storage/legacy.py
qiniu/services/storage/upload_progress_recorder.py
qiniu/services/storage/uploader.py
qiniu/services/storage/uploaders/__init__.py
qiniu/services/storage/uploaders/_default_retrier.py
qiniu/services/storage/uploaders/form_uploader.py
qiniu/services/storage/uploaders/io_chunked.py
qiniu/services/storage/uploaders/resume_uploader_v1.py
qiniu/services/storage/uploaders/resume_uploader_v2.py
qiniu/services/storage/uploaders/abc/__init__.py
qiniu/services/storage/uploaders/abc/resume_uploader_base.py
qiniu/services/storage/uploaders/abc/uploader_base.py
qiniu-7.17.0.dist-info/LICENSE
qiniu-7.17.0.dist-info/METADATA
qiniu-7.17.0.dist-info/WHEEL
qiniu-7.17.0.dist-info/entry_points.txt
qiniu-7.17.0.dist-info/top_level.txt
qiniu-7.17.0.dist-info/RECORD
