Metadata-Version: 2.1
Name: qiniu
Version: 7.17.0
Summary: Qiniu Resource Storage SDK
Home-page: https://github.com/qiniu/python-sdk
Author: Shanghai Qiniu Information Technologies Co., Ltd.
Author-email: sdk@qiniu.com
Maintainer-email: support@qiniu.com
License: MIT
Platform: any
Classifier: Intended Audience :: Developers
Classifier: License :: OSI Approved :: MIT License
Classifier: Operating System :: OS Independent
Classifier: Programming Language :: Python
Classifier: Programming Language :: Python :: 2
Classifier: Programming Language :: Python :: 2.7
Classifier: Programming Language :: Python :: 3
Classifier: Programming Language :: Python :: 3.4
Classifier: Programming Language :: Python :: 3.5
Classifier: Programming Language :: Python :: 3.6
Classifier: Programming Language :: Python :: 3.7
Classifier: Topic :: Internet :: WWW/HTTP :: Dynamic Content
Classifier: Topic :: Software Development :: Libraries :: Python Modules
Provides-Extra: dev
License-File: LICENSE
